generatedateimage/__init__.py
generatedateimage/__main__.py
generatedateimage/app.py
generatedateimage/generatedateimage.py
generatedateimage-0.0.4.dist-info/LICENSE
generatedateimage-0.0.4.dist-info/METADATA
generatedateimage-0.0.4.dist-info/WHEEL
generatedateimage-0.0.4.dist-info/top_level.txt
generatedateimage-0.0.4.dist-info/RECORD
